Metadata-Version: 1.1
Name: mypythonutils
Version: 1.0.1
Summary: A few useful functions
Home-page: UNKNOWN
Author: Paul Gasnier
Author-email: paulgasnier49@gmail.com
License: MIT
Keywords: utils
Platform: UNKNOWN
Classifier: Development Status :: 5 - Production/Stable
Classifier: Intended Audience :: Education
Classifier: Operating System :: Microsoft :: Windows :: Windows 10
Classifier: License :: OSI Approved :: MIT License
Classifier: Programming Language :: Python :: 3
